dlpipeline/__init__.py
dlpipeline/version.py
dlpipeline/augmentor/__init__.py
dlpipeline/augmentor/alb_augmentor.py
dlpipeline/augmentor/dlp_augmentor.py
dlpipeline/augmentor/imgaug_augmentor.py
dlpipeline/augmentor/tf_augmentor.py
dlpipeline/augmentor/experimental/__init__.py
dlpipeline/augmentor/experimental/augmentor_augmentation.py
dlpipeline/augmentor/experimental/keras_augmentations.py
dlpipeline/classifier/__init__.py
dlpipeline/classifier/dlp_classifier.py
dlpipeline/classifier/pt_classifier.py
dlpipeline/classifier/tf_classifier.py
dlpipeline/classifier/persistence/__init__.py
dlpipeline/classifier/persistence/export.py
dlpipeline/classifier/persistence/load.py
dlpipeline/classifier/persistence/save.py
dlpipeline/classifier/tf_imp/__init__.py
dlpipeline/classifier/tf_imp/classification_net.py
dlpipeline/classifier/tf_imp/evaluation.py
dlpipeline/data_loader/__init__.py
dlpipeline/data_loader/dlp_data_loader.py
dlpipeline/data_loader/tf_data_loader.py
dlpipeline/data_loader/image_sets/__init__.py
dlpipeline/data_loader/image_sets/deep_label.py
dlpipeline/data_loader/image_sets/first_level_label.py
dlpipeline/data_loader/image_sets/splits.py
dlpipeline/demo/__init__.py
dlpipeline/demo/dlp_demo.py
dlpipeline/demo/load/__init__.py
dlpipeline/demo/load/loading.py
dlpipeline/demo/python_app/__init__.py
dlpipeline/demo/python_app/python_app.py
dlpipeline/demo/web_app_demo/__init__.py
dlpipeline/demo/web_app_demo/app/__init__.py
dlpipeline/demo/web_app_demo/app/app.py
dlpipeline/demo/web_app_demo/app/config.py
dlpipeline/demo/web_app_demo/app/models/__init__.py
dlpipeline/demo/web_app_demo/app/models/imagenet_class_index.json
dlpipeline/demo/web_app_demo/app/models/model.py
dlpipeline/demo/web_app_demo/app/routes/__init__.py
dlpipeline/demo/web_app_demo/app/routes/uploads.py
dlpipeline/demo/web_app_demo/app/static/favicon.ico
dlpipeline/demo/web_app_demo/app/static/loading_image.gif
dlpipeline/demo/web_app_demo/app/static/style.css
dlpipeline/embedder/__init__.py
DLPipeline-0.1.20190311201423.dist-info/LICENSE.md
DLPipeline-0.1.20190311201423.dist-info/METADATA
DLPipeline-0.1.20190311201423.dist-info/WHEEL
DLPipeline-0.1.20190311201423.dist-info/entry_points.txt
DLPipeline-0.1.20190311201423.dist-info/top_level.txt
DLPipeline-0.1.20190311201423.dist-info/RECORD
