Metadata-Version: 2.1
Name: DLPipeline
Version: 0.1.20190311201423
Summary: Platform for experimenting and Prototyping with Deeplearning.
Home-page: https://bitbucket.com/alexandra-institute/dlpipeline
Author: Christian Heider Nielsen
Author-email: cnheider@yandex.com
Maintainer: Christian Heider Nielsen
Maintainer-email: cnheider@yandex.com
License: Apache License, Version 2.0
Download-URL: https://bitbucket.com/alexandra-institute/dlpipeline/releases
Keywords: python deep learning interface api
Platform: UNKNOWN
Classifier: Development Status :: 4 - Beta
Classifier: Environment :: Console
Classifier: Intended Audience :: End Users/Desktop
Classifier: Intended Audience :: Developers
Classifier: License :: OSI Approved :: Apache Software License
Classifier: Operating System :: MacOS :: MacOS X
Classifier: Operating System :: Microsoft :: Windows
Classifier: Operating System :: POSIX
Classifier: Operating System :: OS Independent
Classifier: Programming Language :: Python :: 3
Classifier: Natural Language :: English
Requires-Python: >=3
Requires-Dist: Cython
Requires-Dist: sklearn
Requires-Dist: albumentations
Requires-Dist: Augmentor
Requires-Dist: matplotlib
Requires-Dist: numpy
Requires-Dist: tqdm
Requires-Dist: h5py
Requires-Dist: scipy
Requires-Dist: tensorflow
Requires-Dist: scikit-image
Requires-Dist: tensorflow-hub
Requires-Dist: pandas
Requires-Dist: flask
Requires-Dist: imgaug
Requires-Dist: warg
Provides-Extra: all
